django_facebook_insights-0.1.0.dist-info/DESCRIPTION.rst
django_facebook_insights-0.1.0.dist-info/METADATA
django_facebook_insights-0.1.0.dist-info/RECORD
django_facebook_insights-0.1.0.dist-info/WHEEL
django_facebook_insights-0.1.0.dist-info/metadata.json
django_facebook_insights-0.1.0.dist-info/top_level.txt
facebook_insights/__init__.py
facebook_insights/exceptions.py
facebook_insights/metrics.py
facebook_insights/models.py
facebook_insights/migrations/__init__.py
