Metadata-Version: 2.0
Name: django-facebook-insights
Version: 0.1.0
Summary: Collect and store Facebook Insights metrics using Django models.
Home-page: https://github.com/nevimov/django-facebook-insights
Author: nevimov
Author-email: nevimov@gmail.com
License: MIT
Keywords: django facebook insights metrics stats statistics
Platform: UNKNOWN
Classifier: Development Status :: 3 - Alpha
Classifier: Environment :: Web Environment
Classifier: Framework :: Django
Classifier: Framework :: Django :: 1.10
Classifier: Framework :: Django :: 1.7
Classifier: Framework :: Django :: 1.8
Classifier: Framework :: Django :: 1.9
Classifier: Intended Audience :: Developers
Classifier: License :: OSI Approved :: MIT License
Classifier: Natural Language :: English
Classifier: Operating System :: OS Independent
Classifier: Programming Language :: Python
Classifier: Programming Language :: Python :: 2
Classifier: Programming Language :: Python :: 2.7
Classifier: Programming Language :: Python :: 3
Classifier: Programming Language :: Python :: 3.4
Classifier: Programming Language :: Python :: 3.5
Classifier: Topic :: Internet :: WWW/HTTP
Requires-Dist: facebook-sdk (>=1,<3)
